time_tracker/__init__.py
time_tracker/cli.py
time_tracker/tracker.py
time_tracker_cli_keerthana-0.1.0.dist-info/LICENSE
time_tracker_cli_keerthana-0.1.0.dist-info/METADATA
time_tracker_cli_keerthana-0.1.0.dist-info/WHEEL
time_tracker_cli_keerthana-0.1.0.dist-info/entry_points.txt
time_tracker_cli_keerthana-0.1.0.dist-info/top_level.txt
time_tracker_cli_keerthana-0.1.0.dist-info/RECORD
