Metadata-Version: 2.1
Name: time-tracker-cli-keerthana
Version: 0.1.0
Summary: A simple CLI tool to track tasks and time logs
Home-page: https://github.com/yourusername/time-tracker-cli
Author: Keerthana P S
Author-email: keerthanaps.work@gmail.com
Classifier: Programming Language :: Python :: 3
Classifier: License :: OSI Approved :: MIT License
Requires-Python: >=3.7
License-File: LICENSE
Requires-Dist: rich
Requires-Dist: matplotlib
